setup.cfg
setup.py
django_headmaster/__init__.py
django_headmaster.egg-info/PKG-INFO
django_headmaster.egg-info/SOURCES.txt
django_headmaster.egg-info/dependency_links.txt
django_headmaster.egg-info/top_level.txt
django_headmaster.egg-info/zip-safe