Metadata-Version: 1.0
Name: django-headmaster
Version: 0.0.1
Summary: Add extra headers to your site via your settings file
Home-page: http://github.com/CyrusBiotechnology/django-headmaster
Author: Peter Novotnak
Author-email: peter@cyrusbio.com
License: MIT
Platform: UNKNOWN
